{
  "test_id": "toolbox-TC003_place_order",
  "name": "User can place order",
  "steps": [
    {
      "action": "navigate",
      "url": "https://practicesoftwaretesting.com/category/hand-tools"
    },
    {
      "action": "click",
      "selector": {
        "strategy": "testid",
        "value": "product-01KKP3FV0NY59TQMVFHG2S7GH4"
      }
    },
    {
      "action": "click",
      "selector": {
        "strategy": "testid",
        "value": "add-to-cart"
      },
      "timeout": 15000
    },
    {
      "action": "click",
      "selector": {
        "strategy": "testid",
        "value": "nav-cart"
      },
      "timeout": 10000
    },
    {
      "action": "navigate",
      "url": "https://practicesoftwaretesting.com/checkout"
    },
    {
      "action": "fill",
      "selector": {
        "strategy": "testid",
        "value": "product-quantity"
      },
      "value": "1"
    },
    {
      "action": "click",
      "selector": {
        "strategy": "testid",
        "value": "proceed-1"
      }
    }
  ],
  "assertions": [
    {
      "type": "url_contains",
      "value": "/checkout"
    }
  ],
  "_meta": {
    "source": "prd_generator",
    "planned_at": "2026-03-14T17:47:08.962290+00:00",
    "locators": 2427,
    "ai_model": "meta-llama/llama-4-scout-17b-16e-instruct"
  }
}